DLite-Python/__init__.py
DLite_Python-0.5.28.data/scripts/dlite-codegen
DLite_Python-0.5.28.data/scripts/dlite-env
DLite_Python-0.5.28.data/scripts/dlite-getuuid
DLite_Python-0.5.28.data/scripts/dlite-validate
DLite_Python-0.5.28.data/scripts/patch-activate.sh
DLite_Python.libs/libbrotlicommon-3bdec5e3.so.1.1.0
DLite_Python.libs/libbrotlidec-c413bb8f.so.1.1.0
DLite_Python.libs/libcares-f1678941.so.2.18.1
DLite_Python.libs/libcrypto-0c766db5.so.3
DLite_Python.libs/libcurl-01d7698e.so.4.8.0
DLite_Python.libs/libidn2-18167d29.so.0.4.0
DLite_Python.libs/libintl-38a1e028.so.8.4.0
DLite_Python.libs/liblzma-ff45e095.so.5.6.2
DLite_Python.libs/libnghttp2-935a8ae8.so.14.28.1
DLite_Python.libs/libpsl-30cc195e.so.5.3.5
DLite_Python.libs/libraptor2-41131f0a.so.0.0.0
DLite_Python.libs/librasqal-b5eb8c7a.so.3.0.0
DLite_Python.libs/librdf-c95bcbb6.so.0.0.0
DLite_Python.libs/libssl-f47d509b.so.3
DLite_Python.libs/libunistring-5b697c8d.so.5.1.0
DLite_Python.libs/libxml2-0da711e3.so.2.12.7
DLite_Python.libs/libxslt-c03155a3.so.1.1.39
DLite_Python.libs/libyajl-a12e0ecd.so.2.1.0
DLite_Python.libs/libzstd-3d3d4524.so.1.5.6
DLite_Python.scripts/dlite-codegen
dlite/__init__.py
dlite/_dlite.so
dlite/datamodel.py
dlite/dataset.py
dlite/dlite.py
dlite/factory.py
dlite/libdlite-utils.so
dlite/libdlite.so
dlite/mappings.py
dlite/options.py
dlite/paths.py
dlite/protocol.py
dlite/quantity.py
dlite/rdf.py
dlite/testutils.py
dlite/utils.py
dlite/share/dlite/LICENSE
dlite/share/dlite/README.md
dlite/share/dlite/bin/dlite-codegen
dlite/share/dlite/bin/dlite-env
dlite/share/dlite/bin/dlite-getuuid
dlite/share/dlite/python-protocol-plugins/file.py
dlite/share/dlite/python-protocol-plugins/http.py
dlite/share/dlite/python-protocol-plugins/sftp.py
dlite/share/dlite/python-storage-plugins/blob.py
dlite/share/dlite/python-storage-plugins/bson.py
dlite/share/dlite/python-storage-plugins/csv.py
dlite/share/dlite/python-storage-plugins/http.py
DLite_Python-0.5.28.dist-info/METADATA
DLite_Python-0.5.28.dist-info/WHEEL
DLite_Python-0.5.28.dist-info/top_level.txt
DLite_Python-0.5.28.dist-info/RECORD
